imaging_transcriptomics/__init__.py
imaging_transcriptomics/bootstrap.py
imaging_transcriptomics/corr.py
imaging_transcriptomics/errors.py
imaging_transcriptomics/genes.py
imaging_transcriptomics/inputs.py
imaging_transcriptomics/log_config.yaml
imaging_transcriptomics/pls.py
imaging_transcriptomics/reporting.py
imaging_transcriptomics/transcriptomics.py
imaging_transcriptomics/data/atlas-desikankilliany_1mm_MNI152.nii.gz
imaging_transcriptomics/data/atlas_regions_info.csv
imaging_transcriptomics/data/fsa5_lh_aparc.annot
imaging_transcriptomics/data/fsa5_rh_aparc.annot
imaging_transcriptomics/data/gene_expression_data.csv
imaging_transcriptomics/data/gene_expression_labels.txt
imaging_transcriptomics/data/geneset_LAKE.gmt
imaging_transcriptomics/data/geneset_Pooled.gmt
imaging_transcriptomics/resources/Header_final.pdf
imaging_transcriptomics/resources/header.png
imaging_transcriptomics/resources/header.svg
imaging_transcriptomics/resources/order_enigma.csv
imaging_transcriptomics/script/__init__.py
imaging_transcriptomics/script/imagingtranscriptomics.py
imaging_transcriptomics/script/imt_gsea.py
imaging_transcriptomics/script/log_config.yaml
tests/__init__.py
tests/auto_test.py
tests/bootstrap_test.py
tests/errors_test.py
tests/genes_test.py
tests/inputs_test.py
tests/transcriptomics_test.py
imaging_transcriptomics-1.1.8.dist-info/LICENSE
imaging_transcriptomics-1.1.8.dist-info/METADATA
imaging_transcriptomics-1.1.8.dist-info/WHEEL
imaging_transcriptomics-1.1.8.dist-info/entry_points.txt
imaging_transcriptomics-1.1.8.dist-info/top_level.txt
imaging_transcriptomics-1.1.8.dist-info/RECORD
