Metadata-Version: 2.1
Name: imaging-transcriptomics
Version: 1.1.8
Summary: A package to perform imaging transcriptomics analysis on a neuroimaging brain scan.
Home-page: https://github.com/alegiac95/Imaging-transcriptomics
Author: Alessio Giacomel, Daniel Martins
Author-email: alessio.giacomel@kcl.ac.uk , daniel.martins@kcl.ac.uk
License: GPLv3
Project-URL: Source, https://github.com/alegiac95/Imaging-transcriptomics
Project-URL: Bug Reports, https://github.com/alegiac95/Imaging-transcriptomics/issues
Project-URL: Documentation, https://imaging-transcriptomics.rtfd.io/
Keywords: Image analysis,Neuroimaging,Imaging Transcriptomics,Medical Imaging,Research,Multimodal Imaging
Platform: UNKNOWN
Classifier: Intended Audience :: Healthcare Industry
Classifier: Intended Audience :: Science/Research
Classifier: Topic :: Scientific/Engineering :: Image Processing
Classifier: Topic :: Scientific/Engineering :: Medical Science Apps.
Classifier: Development Status :: 4 - Beta
Classifier: Programming Language :: Python :: 3
Classifier: Programming Language :: Python :: 3.6
Requires-Dist: h5py (==3.3.0)
Requires-Dist: numpy (==1.21.1)
Requires-Dist: pytest (==6.2.4)
Requires-Dist: tqdm (==4.61.2)
Requires-Dist: scikit-learn (==0.24.2)
Requires-Dist: scipy (==1.7.0)
Requires-Dist: pandas (==1.3.1)
Requires-Dist: joblib (==1.0.1)
Requires-Dist: setuptools (==52.0.0)
Requires-Dist: pyyaml (==5.4.1)
Requires-Dist: statsmodels (==0.12.2)
Requires-Dist: nibabel (==3.2.1)
Requires-Dist: matplotlib (==3.4.2)
Requires-Dist: netneurotools (==0.2.3)
Requires-Dist: gseapy (==0.10.7)
Requires-Dist: nilearn (==0.8.1)
Requires-Dist: enigmatoolbox (==1.1.3)
Requires-Dist: vtk (==9.1.0)
Requires-Dist: numba (==0.55.1)
